Workbook
Name NamedRange1: Sales!$A$33:$E$44

Sheet Sales
E1: SALES(QUANTITY) | P1: REVENUE
A2: DATE | B2: CHAIR KING | C2: TABLE MAGNA | D2: CHAIR MICKY MOUSE | E2: CHAIR SUNRISE | F2: CHAIR FORTUNER | G2: CHAIR SAFARI | H2: CHAIR DOLLAR | I2: STOOL JUPITER | J2: CHAIR SIGMA | K2: CHAIR CRYSTA | L2: TOTAL SALES | M2: CHAIR KING | N2: TABLE MAGNA | O2: CHAIR MICKY MOUSE | P2: CHAIR SUNRISE | Q2: CHAIR FORTUNER | R2: CHAIR SAFARI | S2: CHAIR DOLLAR | T2: STOOL JUPITER | U2: CHAIR SIGMA | V2: CHAIR CRYSTA | W2: TOTAL REVENUE | X2: DATE
A3: 45444 | B3: 64 | C3: 12 | D3: 75 | E3: 32 | F3: 0 | G3: 0 | H3: 16 | I3: 0 | J3: 0 | K3: 0 | L3: =SUM(B3:K3) -> 199 | M3: =B3*201 -> 12864 | N3: =C3*194 -> 2328 | O3: =D3*88 -> 6600 | P3: =E3*PL!$D$5 -> 5312 | Q3: =F3*PL!$D$6 -> 0 | R3: =G3*PL!$D$7 -> 0 | S3: =H3*PL!$D$8 -> 2944 | T3: =I3*PL!$D$9 -> 0 | U3: =J3*PL!$D$10 -> 0 | V3: =K3*PL!$D$11 -> 0 | W3: =SUM(M3:V3) -> 30048 | X3: 45444
A4: 45445 | B4: 44 | C4: 0 | D4: 0 | E4: 48 | F4: 96 | G4: 48 | H4: 16 | I4: 0 | J4: 0 | K4: 0 | L4: =SUM(B4:K4) -> 252 | M4: =B4*201 -> 8844 | N4: =C4*194 -> 0 | O4: =D4*88 -> 0 | P4: =E4*PL!$D$5 -> 7968 | Q4: =F4*PL!$D$6 -> 27360 | R4: =G4*PL!$D$7 -> 11760 | S4: =H4*PL!$D$8 -> 2944 | T4: =I4*PL!$D$9 -> 0 | U4: =J4*PL!$D$10 -> 0 | V4: =K4*PL!$D$11 -> 0 | W4: =SUM(M4:V4) -> 58876 | X4: 45445
A5: 45446 | B5: 48 | C5: 0 | D5: 0 | E5: 0 | F5: 80 | G5: 100 | H5: 0 | I5: 10 | J5: 0 | K5: 0 | L5: =SUM(B5:K5) -> 238 | M5: =B5*201 -> 9648 | N5: =C5*194 -> 0 | O5: =D5*88 -> 0 | P5: =E5*PL!$D$5 -> 0 | Q5: =F5*PL!$D$6 -> 22800 | R5: =G5*PL!$D$7 -> 24500 | S5: =H5*PL!$D$8 -> 0 | T5: =I5*PL!$D$9 -> 900 | U5: =J5*PL!$D$10 -> 0 | V5: =K5*PL!$D$11 -> 0 | W5: =SUM(M5:V5) -> 57848 | X5: 45446
A6: 45447 | B6: 48 | C6: 0 | D6: 0 | E6: 0 | F6: 30 | G6: 0 | H6: 25 | I6: 10 | J6: 36 | K6: 100 | L6: =SUM(B6:K6) -> 249 | M6: =B6*201 -> 9648 | N6: =C6*194 -> 0 | O6: =D6*88 -> 0 | P6: =E6*PL!$D$5 -> 0 | Q6: =F6*PL!$D$6 -> 8550 | R6: =G6*PL!$D$7 -> 0 | S6: =H6*PL!$D$8 -> 4600 | T6: =I6*PL!$D$9 -> 900 | U6: =J6*PL!$D$10 -> 7380 | V6: =K6*PL!$D$11 -> 21500 | W6: =SUM(M6:V6) -> 52578 | X6: 45447
A7: 45448 | B7: 48 | C7: 34 | D7: 0 | E7: 48 | F7: 30 | G7: 48 | H7: 64 | I7: 10 | J7: 0 | K7: 100 | L7: =SUM(B7:K7) -> 382 | M7: =B7*201 -> 9648 | N7: =C7*194 -> 6596 | O7: =D7*88 -> 0 | P7: =E7*PL!$D$5 -> 7968 | Q7: =F7*PL!$D$6 -> 8550 | R7: =G7*PL!$D$7 -> 11760 | S7: =H7*PL!$D$8 -> 11776 | T7: =I7*PL!$D$9 -> 900 | U7: =J7*PL!$D$10 -> 0 | V7: =K7*PL!$D$11 -> 21500 | W7: =SUM(M7:V7) -> 78698 | X7: 45448
A8: 45449 | B8: 0 | C8: 0 | D8: 0 | E8: =32+48 -> 80 | F8: 0 | G8: 0 | H8: 32 | I8: 12 | J8: 48 | K8: 0 | L8: =SUM(B8:K8) -> 172 | M8: =B8*201 -> 0 | N8: =C8*194 -> 0 | O8: =D8*88 -> 0 | P8: =E8*PL!$D$5 -> 13280 | Q8: =F8*PL!$D$6 -> 0 | R8: =G8*PL!$D$7 -> 0 | S8: =H8*PL!$D$8 -> 5888 | T8: =I8*PL!$D$9 -> 1080 | U8: =J8*PL!$D$10 -> 9840 | V8: =K8*PL!$D$11 -> 0 | W8: =SUM(M8:V8) -> 30088 | X8: 45449
A9: 45450 | B9: 24 | C9: 16 | D9: 0 | E9: 64 | F9: 60 | G9: 0 | H9: 80 | I9: 15 | J9: 0 | K9: 0 | L9: =SUM(B9:K9) -> 259 | M9: =B9*201 -> 4824 | N9: =C9*194 -> 3104 | O9: =D9*88 -> 0 | P9: =E9*PL!$D$5 -> 10624 | Q9: =F9*PL!$D$6 -> 17100 | R9: =G9*PL!$D$7 -> 0 | S9: =H9*PL!$D$8 -> 14720 | T9: =I9*PL!$D$9 -> 1350 | U9: =J9*PL!$D$10 -> 0 | V9: =K9*PL!$D$11 -> 0 | W9: =SUM(M9:V9) -> 51722 | X9: 45450
A10: 45451 | B10: 0 | C10: =22+15 -> 37 | D10: 12 | E10: 48 | F10: 0 | G10: 0 | H10: 64 | I10: 0 | J10: 0 | K10: 0 | L10: =SUM(B10:K10) -> 161 | M10: =B10*201 -> 0 | N10: =C10*194 -> 7178 | O10: =D10*88 -> 1056 | P10: =E10*PL!$D$5 -> 7968 | Q10: =F10*PL!$D$6 -> 0 | R10: =G10*PL!$D$7 -> 0 | S10: =H10*PL!$D$8 -> 11776 | T10: =I10*PL!$D$9 -> 0 | U10: =J10*PL!$D$10 -> 0 | V10: =K10*PL!$D$11 -> 0 | W10: =SUM(M10:V10) -> 27978 | X10: 45451
A11: 45452 | B11: 84 | C11: 35 | D11: 0 | E11: 112 | F11: 80 | G11: 0 | H11: 16 | I11: 0 | J11: 0 | K11: 0 | L11: =SUM(B11:K11) -> 327 | M11: =B11*201 -> 16884 | N11: =C11*194 -> 6790 | O11: =D11*88 -> 0 | P11: =E11*PL!$D$5 -> 18592 | Q11: =F11*PL!$D$6 -> 22800 | R11: =G11*PL!$D$7 -> 0 | S11: =H11*PL!$D$8 -> 2944 | T11: =I11*PL!$D$9 -> 0 | U11: =J11*PL!$D$10 -> 0 | V11: =K11*PL!$D$11 -> 0 | W11: =SUM(M11:V11) -> 68010 | X11: 45452
A12: 45453 | B12: 48 | C12: 32 | D12: 0 | E12: =64+32 -> 96 | F12: 72 | G12: 0 | H12: =64+64 -> 128 | I12: 0 | J12: 0 | K12: 150 | L12: =SUM(B12:K12) -> 526 | M12: =B12*201 -> 9648 | N12: =C12*194 -> 6208 | O12: =D12*88 -> 0 | P12: =E12*PL!$D$5 -> 15936 | Q12: =F12*PL!$D$6 -> 20520 | R12: =G12*PL!$D$7 -> 0 | S12: =H12*PL!$D$8 -> 23552 | T12: =I12*PL!$D$9 -> 0 | U12: =J12*PL!$D$10 -> 0 | V12: =K12*PL!$D$11 -> 32250 | W12: =SUM(M12:V12) -> 108114 | X12: 45453
A13: 45455 | B13: 84 | C13: 15 | D13: 25 | E13: 80 | F13: 12 | G13: 0 | H13: =16+32 -> 48 | I13: 50 | J13: 24 | K13: 0 | L13: =SUM(B13:K13) -> 338 | M13: =B13*201 -> 16884 | N13: =C13*194 -> 2910 | O13: =D13*88 -> 2200 | P13: =E13*PL!$D$5 -> 13280 | Q13: =F13*PL!$D$6 -> 3420 | R13: =G13*PL!$D$7 -> 0 | S13: =H13*PL!$D$8 -> 8832 | T13: =I13*PL!$D$9 -> 4500 | U13: =J13*PL!$D$10 -> 4920 | V13: =K13*PL!$D$11 -> 0 | W13: =SUM(M13:V13) -> 56946 | X13: 45455
A14: 45456 | B14: 54 | C14: 17 | D14: 0 | E14: 0 | F14: 0 | G14: 0 | H14: 128 | I14: 20 | J14: 0 | K14: 0 | L14: =SUM(B14:K14) -> 219 | M14: =B14*201 -> 10854 | N14: =C14*194 -> 3298 | O14: =D14*88 -> 0 | P14: =E14*PL!$D$5 -> 0 | Q14: =F14*PL!$D$6 -> 0 | R14: =G14*PL!$D$7 -> 0 | S14: =H14*PL!$D$8 -> 23552 | T14: =I14*PL!$D$9 -> 1800 | U14: =J14*PL!$D$10 -> 0 | V14: =K14*PL!$D$11 -> 0 | W14: =SUM(M14:V14) -> 39504 | X14: 45456
A15: 45457 | B15: 80 | C15: 0 | D15: 0 | E15: 80 | F15: 32 | G15: 48 | H15: 112 | I15: 70 | J15: 36 | K15: 0 | L15: =SUM(B15:K15) -> 458 | M15: =B15*201 -> 16080 | N15: =C15*194 -> 0 | O15: =D15*88 -> 0 | P15: =E15*PL!$D$5 -> 13280 | Q15: =F15*PL!$D$6 -> 9120 | R15: =G15*PL!$D$7 -> 11760 | S15: =H15*PL!$D$8 -> 20608 | T15: =I15*PL!$D$9 -> 6300 | U15: =J15*PL!$D$10 -> 7380 | V15: =K15*PL!$D$11 -> 0 | W15: =SUM(M15:V15) -> 84528 | X15: 45457
A16: 45458 | B16: 64 | C16: 0 | D16: 0 | E16: =16+32 -> 48 | F16: 0 | G16: 0 | H16: 32 | I16: 12 | J16: 0 | K16: 0 | L16: =SUM(B16:K16) -> 156 | M16: =B16*201 -> 12864 | N16: =C16*194 -> 0 | O16: =D16*88 -> 0 | P16: =E16*PL!$D$5 -> 7968 | Q16: =F16*PL!$D$6 -> 0 | R16: =G16*PL!$D$7 -> 0 | S16: =H16*PL!$D$8 -> 5888 | T16: =I16*PL!$D$9 -> 1080 | U16: =J16*PL!$D$10 -> 0 | V16: =K16*PL!$D$11 -> 0 | W16: =SUM(M16:V16) -> 27800 | X16: 45458
A17: 45459 | B17: 32 | C17: 10 | D17: 50 | E17: =128+16 -> 144 | F17: 42 | G17: 100 | H17: 16 | I17: 0 | J17: 0 | K17: 0 | L17: =SUM(B17:K17) -> 394 | M17: =B17*201 -> 6432 | N17: =C17*194 -> 1940 | O17: =D17*88 -> 4400 | P17: =E17*PL!$D$5 -> 23904 | Q17: =F17*PL!$D$6 -> 11970 | R17: =G17*PL!$D$7 -> 24500 | S17: =H17*PL!$D$8 -> 2944 | T17: =I17*PL!$D$9 -> 0 | U17: =J17*PL!$D$10 -> 0 | V17: =K17*PL!$D$11 -> 0 | W17: =SUM(M17:V17) -> 76090 | X17: 45459
A18: 45461 | B18: 48 | C18: 10 | D18: 0 | E18: 0 | F18: 0 | G18: 0 | H18: 48 | I18: 40 | J18: 0 | K18: 0 | L18: =SUM(B18:K18) -> 146 | M18: =B18*201 -> 9648 | N18: =C18*194 -> 1940 | O18: =D18*88 -> 0 | P18: =E18*PL!$D$5 -> 0 | Q18: =F18*PL!$D$6 -> 0 | R18: =G18*PL!$D$7 -> 0 | S18: =H18*PL!$D$8 -> 8832 | T18: =I18*PL!$D$9 -> 3600 | U18: =J18*PL!$D$10 -> 0 | V18: =K18*PL!$D$11 -> 0 | W18: =SUM(M18:V18) -> 24020 | X18: 45461
A19: 45462 | B19: 64 | C19: 0 | D19: 5 | E19: 184 | F19: 72 | G19: 48 | H19: 48 | I19: 20 | J19: 0 | K19: 0 | L19: =SUM(B19:K19) -> 441 | M19: =B19*201 -> 12864 | N19: =C19*194 -> 0 | O19: =D19*88 -> 440 | P19: =E19*PL!$D$5 -> 30544 | Q19: =F19*PL!$D$6 -> 20520 | R19: =G19*PL!$D$7 -> 11760 | S19: =H19*PL!$D$8 -> 8832 | T19: =I19*PL!$D$9 -> 1800 | U19: =J19*PL!$D$10 -> 0 | V19: =K19*PL!$D$11 -> 0 | W19: =SUM(M19:V19) -> 86760 | X19: 45462
A20: 45464 | B20: 24 | C20: 0 | D20: 0 | E20: =64+64 -> 128 | F20: 0 | G20: 48 | H20: 32 | I20: 0 | J20: 32 | K20: 25 | L20: =SUM(B20:K20) -> 289 | M20: =B20*201 -> 4824 | N20: =C20*194 -> 0 | O20: =D20*88 -> 0 | P20: =E20*PL!$D$5 -> 21248 | Q20: =F20*PL!$D$6 -> 0 | R20: =G20*PL!$D$7 -> 11760 | S20: =H20*PL!$D$8 -> 5888 | T20: =I20*PL!$D$9 -> 0 | U20: =J20*PL!$D$10 -> 6560 | V20: =K20*PL!$D$11 -> 5375 | W20: =SUM(M20:V20) -> 55655 | X20: 45464
A21: 45465 | B21: 48 | C21: 0 | D21: 0 | E21: 32 | F21: 0 | G21: 0 | H21: 72 | I21: 10 | J21: 48 | K21: 0 | L21: =SUM(B21:K21) -> 210 | M21: =B21*201 -> 9648 | N21: =C21*194 -> 0 | O21: =D21*88 -> 0 | P21: =E21*PL!$D$5 -> 5312 | Q21: =F21*PL!$D$6 -> 0 | R21: =G21*PL!$D$7 -> 0 | S21: =H21*PL!$D$8 -> 13248 | T21: =I21*PL!$D$9 -> 900 | U21: =J21*PL!$D$10 -> 9840 | V21: =K21*PL!$D$11 -> 0 | W21: =SUM(M21:V21) -> 38948 | X21: 45465
A22: 45466 | B22: 48 | C22: 6 | D22: 0 | E22: =64+96 -> 160 | F22: 60 | G22: 48 | H22: =32+48 -> 80 | I22: 0 | J22: 32 | K22: 0 | L22: =SUM(B22:K22) -> 434 | M22: =B22*201 -> 9648 | N22: =C22*194 -> 1164 | O22: =D22*88 -> 0 | P22: =E22*PL!$D$5 -> 26560 | Q22: =F22*PL!$D$6 -> 17100 | R22: =G22*PL!$D$7 -> 11760 | S22: =H22*PL!$D$8 -> 14720 | T22: =I22*PL!$D$9 -> 0 | U22: =J22*PL!$D$10 -> 6560 | V22: =K22*PL!$D$11 -> 0 | W22: =SUM(M22:V22) -> 87512 | X22: 45466
A23: 45467 | B23: 12 | C23: 0 | D23: 10 | E23: 78 | F23: 0 | G23: 0 | H23: 32 | I23: 10 | J23: 0 | K23: 0 | L23: =SUM(B23:K23) -> 142 | M23: =B23*201 -> 2412 | N23: =C23*194 -> 0 | O23: =D23*88 -> 880 | P23: =E23*PL!$D$5 -> 12948 | Q23: =F23*PL!$D$6 -> 0 | R23: =G23*PL!$D$7 -> 0 | S23: =H23*PL!$D$8 -> 5888 | T23: =I23*PL!$D$9 -> 900 | U23: =J23*PL!$D$10 -> 0 | V23: =K23*PL!$D$11 -> 0 | W23: =SUM(M23:V23) -> 23028 | X23: 45467
A24: 45468 | B24: 60 | C24: 24 | D24: 0 | E24: =80+64 -> 144 | F24: 0 | G24: 0 | H24: 185 | I24: =20+50 -> 70 | J24: 0 | K24: 24 | L24: =SUM(B24:K24) -> 507 | M24: =B24*201 -> 12060 | N24: =C24*194 -> 4656 | O24: =D24*88 -> 0 | P24: =E24*PL!$D$5 -> 23904 | Q24: =F24*PL!$D$6 -> 0 | R24: =G24*PL!$D$7 -> 0 | S24: =H24*PL!$D$8 -> 34040 | T24: =I24*PL!$D$9 -> 6300 | U24: =J24*PL!$D$10 -> 0 | V24: =K24*PL!$D$11 -> 5160 | W24: =SUM(M24:V24) -> 86120 | X24: 45468
A25: 45469 | B25: 106 | C25: 26 | D25: 0 | E25: 32 | F25: 16 | G25: =64+96 -> 160 | H25: =80+16 -> 96 | I25: =105+60 -> 165 | J25: 0 | K25: 50 | L25: =SUM(B25:K25) -> 651 | M25: =B25*201 -> 21306 | N25: =C25*194 -> 5044 | O25: =D25*88 -> 0 | P25: =E25*PL!$D$5 -> 5312 | Q25: =F25*PL!$D$6 -> 4560 | R25: =G25*PL!$D$7 -> 39200 | S25: =H25*PL!$D$8 -> 17664 | T25: =I25*PL!$D$9 -> 14850 | U25: =J25*PL!$D$10 -> 0 | V25: =K25*PL!$D$11 -> 10750 | W25: =SUM(M25:V25) -> 118686 | X25: 45469
A26: 45470 | B26: 48 | C26: 0 | D26: 10 | E26: 72 | F26: 60 | G26: 80 | H26: 36 | I26: 20 | J26: 0 | K26: 0 | L26: =SUM(B26:K26) -> 326 | M26: =B26*201 -> 9648 | N26: =C26*194 -> 0 | O26: =D26*88 -> 880 | P26: =E26*PL!$D$5 -> 11952 | Q26: =F26*PL!$D$6 -> 17100 | R26: =G26*PL!$D$7 -> 19600 | S26: =H26*PL!$D$8 -> 6624 | T26: =I26*PL!$D$9 -> 1800 | U26: =J26*PL!$D$10 -> 0 | V26: =K26*PL!$D$11 -> 0 | W26: =SUM(M26:V26) -> 67604 | X26: 45470
A27: 45471 | B27: 60 | C27: 9 | D27: 0 | E27: 48 | F27: 60 | G27: =48+80 -> 128 | H27: =48+32 -> 80 | I27: 10 | J27: 16 | K27: 0 | L27: =SUM(B27:K27) -> 411 | M27: =B27*201 -> 12060 | N27: =C27*194 -> 1746 | O27: =D27*88 -> 0 | P27: =E27*PL!$D$5 -> 7968 | Q27: =F27*PL!$D$6 -> 17100 | R27: =G27*PL!$D$7 -> 31360 | S27: =H27*PL!$D$8 -> 14720 | T27: =I27*PL!$D$9 -> 900 | U27: =J27*PL!$D$10 -> 3280 | V27: =K27*PL!$D$11 -> 0 | W27: =SUM(M27:V27) -> 89134 | X27: 45471
A28: 45472 | B28: 24 | C28: 38 | D28: 20 | E28: =128+48 -> 176 | F28: 0 | G28: 0 | H28: 72 | I28: 23 | J28: 0 | K28: 0 | L28: =SUM(B28:K28) -> 353 | M28: =B28*201 -> 4824 | N28: =C28*194 -> 7372 | O28: =D28*88 -> 1760 | P28: =E28*PL!$D$5 -> 29216 | Q28: =F28*PL!$D$6 -> 0 | R28: =G28*PL!$D$7 -> 0 | S28: =H28*PL!$D$8 -> 13248 | T28: =I28*PL!$D$9 -> 2070 | U28: =J28*PL!$D$10 -> 0 | V28: =K28*PL!$D$11 -> 0 | W28: =SUM(M28:V28) -> 58490 | X28: 45472
A29: 45473 | B29: 16 | C29: 8 | D29: 0 | E29: =48+32 -> 80 | F29: 0 | G29: 32 | H29: 32 | I29: 20 | J29: 16 | K29: 0 | L29: =SUM(B29:K29) -> 204 | M29: =B29*201 -> 3216 | N29: =C29*194 -> 1552 | O29: =D29*88 -> 0 | P29: =E29*PL!$D$5 -> 13280 | Q29: =F29*PL!$D$6 -> 0 | R29: =G29*PL!$D$7 -> 7840 | S29: =H29*PL!$D$8 -> 5888 | T29: =I29*PL!$D$9 -> 1800 | U29: =J29*PL!$D$10 -> 3280 | V29: =K29*PL!$D$11 -> 0 | W29: =SUM(M29:V29) -> 36856 | X29: 45473
A30: TOTAL | B30: =SUM(B3:B29) -> 1280 | C30: =SUM(C3:C29) -> 329 | D30: =SUM(D3:D29) -> 207 | E30: =SUM(E3:E29) -> 2014 | F30: =SUM(F3:F29) -> 802 | G30: =SUM(G3:G29) -> 888 | H30: =SUM(H3:H29) -> 1590 | I30: =SUM(I3:I29) -> 597 | ... K30: =SUM(K3:K29) -> 449 | M30: =SUM(M3:M29) -> 257280 | N30: =SUM(N3:N29) -> 63826 | O30: =SUM(O3:O29) -> 18216 | P30: =SUM(P3:P29) -> 334324 | Q30: =SUM(Q3:Q29) -> 228570 | R30: =SUM(R3:R29) -> 217560 | S30: =SUM(S3:S29) -> 292560 | T30: =SUM(T3:T29) -> 53730 | ... V30: =SUM(V3:V29) -> 96535 | W30: =SUM(M30:V30) -> 1621641
M31: CHAIR KING | N31: TABLE MAGNA | O31: CHAIR MICKY MOUSE | P31: CHAIR SUNRISE | Q31: CHAIR FORTUNER | R31: CHAIR SAFARI | S31: CHAIR DOLLAR | T31: STOOL JUPITER | U31: CHAIR SIGMA | V31: CHAIR CRYSTA
V32: Standard Deviation | W32: =STDEV(W3:W29) -> 26435.378
V33: Average Daily Sales | W33: =AVERAGE(W3:W29) -> 60060.778
V34: Maximum Sale | W34: =MAX(W3:W29) -> 118686
V35: Minimum Sale | W35: =MIN(W3:W29) -> 23028

Sheet Inventory
D1: Purchasing Dates
A2: SKU | C2: Initial Inventory | D2: 45446 | E2: 45464 | F2: End Inventory | G2: Average Inventory | H2: Average Sales | I2: SKU
A3: CHAIR KING | C3: 256 | D3: 960 | E3: 400 | F3: =C3+E3+D3-1280 -> 336 | G3: =(C3+D3+E3) -> 1616 | H3: 1280 | I3: CHAIR KING
A4: TABLE MAGNA | C4: 30 | D4: 250 | E4: 200 | F4: =C4+E4+D4-329 -> 151 | G4: =(C4+D4+E4) -> 480 | H4: 329 | I4: TABLE MAGNA
A5: CHAIR MICKY MOUSE | C5: 100 | D5: 150 | E5: 150 | F5: =C5+E5+D5-207 -> 193 | G5: =(C5+D5+E5) -> 400 | H5: 207 | I5: CHAIR MICKY MOUSE
A6: CHAIR SUNRISE | C6: 160 | D6: 1500 | E6: 1200 | F6: =C6+E6+D6-2014 -> 846 | G6: =(C6+D6+E6) -> 2860 | H6: 2014 | I6: CHAIR SUNRISE
A7: CHAIR FORTUNER | C7: 240 | D7: 660 | E7: 400 | F7: =C7+E7+D7-802 -> 498 | G7: =(C7+D7+E7) -> 1300 | H7: 802 | I7: CHAIR FORTUNER
A8: CHAIR SAFARI | C8: 208 | D8: 432 | E8: 560 | F8: =C8+E8+D8-888 -> 312 | G8: =(C8+D8+E8) -> 1200 | H8: 888 | I8: CHAIR SAFARI
A9: CHAIR DOLLAR | C9: 176 | D9: 1040 | E9: 1200 | F9: =C9+E9+D9-1590 -> 826 | G9: =(C9+D9+E9) -> 2416 | H9: 1590 | I9: CHAIR DOLLAR
A10: STOOL JUPITER | C10: 60 | D10: 300 | E10: 300 | F10: =C10+E10+D10-597 -> 63 | G10: =(C10+D10+E10) -> 660 | H10: 597 | I10: STOOL JUPITER
A11: CHAIR SIGMA | C11: 60 | D11: 84 | E11: 208 | F11: =C11+D11+E11-228 -> 124 | G11: =(C11+D11+E11) -> 352 | H11: 288 | I11: CHAIR SIGMA
A12: CHAIR CRYSTA | C12: 0 | D12: 350 | E12: 500 | F12: =C12+E12+D12-449 -> 401 | G12: =(C12+D12+E12) -> 850 | H12: 449 | I12: CHAIR CRYSTA

Sheet PL
A1: SKU | C1: COST PRICE | D1: SELLING PRICE | E1: PROFIT | F1: PROFIT %
A2: CHAIR KING | C2: 191 | D2: 201 | E2: =D2-C2 -> 10 | F2: =(D2-C2)/C2 -> 0.052356021
A3: TABLE MAGNA | C3: 185 | D3: 194 | E3: =D3-C3 -> 9 | F3: =(D3-C3)/C3 -> 0.048648649
A4: CHAIR MICKY MOUSE | C4: 84 | D4: 88 | E4: =D4-C4 -> 4 | F4: =(D4-C4)/C4 -> 0.047619048
A5: CHAIR SUNRISE | C5: 149 | D5: 166 | E5: =D5-C5 -> 17 | F5: =(D5-C5)/C5 -> 0.11409396
A6: CHAIR FORTUNER | C6: 231 | D6: 285 | E6: =D6-C6 -> 54 | F6: =(D6-C6)/C6 -> 0.23376623
A7: CHAIR SAFARI | C7: 221 | D7: 245 | E7: =D7-C7 -> 24 | F7: =(D7-C7)/C7 -> 0.10859729
A8: CHAIR DOLLAR | C8: 165 | D8: 184 | E8: =D8-C8 -> 19 | F8: =(D8-C8)/C8 -> 0.11515152
A9: STOOL JUPITER | C9: 86 | D9: 90 | E9: =D9-C9 -> 4 | F9: =(D9-C9)/C9 -> 0.046511628
A10: CHAIR SIGMA | C10: 158 | D10: 205 | E10: =D10-C10 -> 47 | F10: =(D10-C10)/C10 -> 0.29746835
A11: CHAIR CRYSTA | C11: 204 | D11: 215 | E11: =D11-C11 -> 11 | F11: =(D11-C11)/C11 -> 0.053921569
A15: SKU | C15: TOTAL COST | D15: TOTAL REVENUE | E15: PROFIT | F15: PROFIT % OF TOTAL | G15: CUMULATIVE PROFIT % | H15: % OF TOTAL REVENUE
A16: CHAIR FORTUNER | C16: 185262 | D16: 228570 | E16: 43308 | F16: 0.26007687 | G16: =F16 -> 0.26007687 | H16: =D16/$D$26 -> 0.14094982
A17: CHAIR SUNRISE | C17: 300086 | D17: 334324 | E17: 34238 | F17: 0.20560894 | G17: =G16+F17 -> 0.4656858 | H17: =D17/$D$26 -> 0.206164
A18: CHAIR DOLLAR | C18: 262350 | D18: 292560 | E18: 30210 | F18: 0.18141965 | G18: =G17+F18 -> 0.64710545 | H18: =D18/$D$26 -> 0.18040984
A19: CHAIR SAFARI | C19: 196248 | D19: 217560 | E19: 21312 | F19: 0.12798463 | G19: =G18+F19 -> 0.77509008 | H19: =D19/$D$26 -> 0.1341604
A20: CHAIR SIGMA | C20: 45504 | D20: 59040 | E20: 13536 | F20: 0.081287533 | G20: =G19+F20 -> 0.85637761 | H20: =D20/$D$26 -> 0.036407565
A21: CHAIR KING | C21: 244480 | D21: 257280 | E21: 12800 | F21: 0.076867644 | G21: =G20+F21 -> 0.93324526 | H21: =D21/$D$26 -> 0.1586541
A22: CHAIR CRYSTA | C22: 91596 | D22: 96535 | E22: 4939 | F22: 0.029660101 | G22: =G21+F22 -> 0.96290536 | H22: =D22/$D$26 -> 0.059529205
A23: TABLE MAGNA | C23: 60865 | D23: 63826 | E23: 2961 | F23: 0.017781648 | G23: =G22+F23 -> 0.980687 | H23: =D23/$D$26 -> 0.039358896
A24: STOOL JUPITER | C24: 51342 | D24: 53730 | E24: 2388 | F24: 0.01434062 | G24: =G23+F24 -> 0.99502762 | H24: =D24/$D$26 -> 0.033133104
A25: CHAIR MICKY MOUSE | C25: 17388 | D25: 18216 | E25: 828 | F25: 0.0049723757 | G25: =G24+F25 -> 1 | H25: =D25/$D$26 -> 0.011233066
A26: TOTAL | C26: 1455121 | D26: 1621641 | E26: 166520
A28: PRODUCT | B28: % OF TOTAL REVENUE | C28: CUMULATIVE %
A29: CHAIR SUNRISE | B29: 0.2062 | C29: 0.2062
A30: CHAIR DOLLAR | B30: 0.1804 | C30: 0.3866
A31: CHAIR KING | B31: 0.1587 | C31: 0.5453
A32: CHAIR FORTUNER | B32: 0.1409 | C32: 0.6862
A33: CHAIR SAFARI | B33: 0.1342 | C33: 0.8204
A34: CHAIR CRYSTA | B34: 0.0595 | C34: 0.8799
A35: TABLE MAGNA | B35: 0.0394 | C35: 0.9193
A36: CHAIR SIGMA | B36: 0.0364 | C36: 0.9557
A37: STOOL JUPITER | B37: 0.0331 | C37: 0.9888
A38: CHAIR MICKY MOUSE | B38: 0.0112 | C38: 1
A40: Class A | B40: Class B | C40: Class C
A41: CHAIR SUNRISE | B41: CHAIR CRYSTA | C41: STOOL JUPITER
A42: CHAIR DOLLAR | B42: TABLE MAGNA | C42: CHAIR MICKY MOUSE
A43: CHAIR KING | B43: CHAIR SIGMA
A44: CHAIR FORTUNER
A45: CHAIR SAFARI

Sheet PL Insights
A1: Fixed Cost Analysis | D1: Salaries
B2: COST | E2: COST
A3: ELECTRICITY | B3: 2300 | D3: Staff 1 | E3: 6000
A4: Salaries | B4: 64000 | D4: Staff 2 | E4: 7000
A5: Unloading | B5: 3600 | D5: Staff 3 | E5: 6000
A6: TOTAL FIXED COST | B6: =SUM(B3:B5) -> 69900 | D6: Owner | E6: 45000
D7: TOTAL SALARIES | E7: =SUM(E3:E6) -> 64000
A10: BALENCE SHEET
A11: VARIABLES | B11: VALUE | C11: REMARK
A12: TOTAL REVENUE | B12: 1621641 | C12: FARELY GOOD
A13: GROSS PROFIT | B13: 166520
A14: NORMALISED FIXED COSTS | B14: 69900 | C14: MAJORLY FROM MONTHLY FIXED EXPENSES
A15: NET PROFIT | B15: =B13-B14 -> 96620
A16: GROSS PROFIT RATIO | B16: =B13/B12 -> 0.10268611
A17: NET PROFIT RATIO | B17: =B15/B12 -> 0.059581621 | C17: FARELY GOOD FOR A WHOLESALE STORE
